LICENSE
flatehr/__init__.py
flatehr/build.py
flatehr/cli/__init__.py
flatehr/cli/entrypoint.py
flatehr/cli/generate.py
flatehr/cli/inspect_template.py
flatehr/core.py
flatehr/factory.py
flatehr/impl/__init__.py
flatehr/impl/anytree_core.py
flatehr/sources/__init__.py
flatehr/sources/base.py
flatehr/sources/json.py
flatehr/sources/xml.py
flatehr-1.2.0.dist-info/entry_points.txt
flatehr-1.2.0.dist-info/LICENSE
flatehr-1.2.0.dist-info/WHEEL
flatehr-1.2.0.dist-info/METADATA
flatehr-1.2.0.dist-info/RECORD
