Metadata-Version: 2.1
Name: flatehr
Version: 1.2.0
Summary: Tool for generating openEHR compositions from other formats
Home-page: https://github.com/crs4/flatehr
License: GPL-3.0-only
Author: Mauro Del Rio
Author-email: mauro@crs4.it
Requires-Python: >=3.8,<4.0
Classifier: License :: OSI Approved :: GNU General Public License v3 (GPLv3)
Classifier: Programming Language :: Python :: 3
Classifier: Programming Language :: Python :: 3.8
Classifier: Programming Language :: Python :: 3.9
Classifier: Programming Language :: Python :: 3.10
Classifier: Programming Language :: Python :: 3.11
Requires-Dist: Jinja2 (>=3.1.2,<4.0.0)
Requires-Dist: anytree (==2.8.0)
Requires-Dist: defopt (>=6.4.0,<7.0.0)
Requires-Dist: jq (>=1.2.2,<2.0.0)
Requires-Dist: jsonpath-ng (>=1.5.3,<2.0.0)
Requires-Dist: lxml (>=4.9.0,<5.0.0)
Requires-Dist: pipe (>=2.0,<3.0)
Requires-Dist: pyaml (>=21.10.1,<22.0.0)
Requires-Dist: python-dateutil (>=2.8.2,<3.0.0)
Requires-Dist: python-semantic-release (>=7.31.4,<8.0.0)
Project-URL: Repository, https://github.com/crs4/flatehr
